arivo/__init__.py
arivo/const.py
arivo-1.0.3.dist-info/AUTHORS
arivo-1.0.3.dist-info/LICENSE
arivo-1.0.3.dist-info/METADATA
arivo-1.0.3.dist-info/WHEEL
arivo-1.0.3.dist-info/pbr.json
arivo-1.0.3.dist-info/top_level.txt
arivo-1.0.3.dist-info/RECORD
