Metadata-Version: 2.1
Name: arivo
Version: 1.0.3
Summary: Base python package for the ARIVO Python SDK
Home-page: https://gitlab.com/arivo-public/arivo-python.git
Author: ARIVO
Author-email: support@arivo.co
License: MIT
Keywords: arivo webhook api
Platform: UNKNOWN
Classifier: Intended Audience :: Developers
Classifier: License :: OSI Approved :: MIT License
Classifier: Programming Language :: Python
Classifier: Programming Language :: Python :: 3.6
Classifier: Programming Language :: Python :: 3.7
Classifier: Programming Language :: Python :: 3.8
Provides-Extra: all
Requires-Dist: arivo-webhook (<2,>=1.0) ; extra == 'all'
Requires-Dist: arivo-api (<2,>=1.0) ; extra == 'all'
Provides-Extra: test
Requires-Dist: pytest ; extra == 'test'
Requires-Dist: pytest-cov ; extra == 'test'
